commonlytools/__init__.py
commonlytools/discohook.py
commonlytools/error.py
CommonlyTools-2.1.3.dist-info/LICENSE
CommonlyTools-2.1.3.dist-info/METADATA
CommonlyTools-2.1.3.dist-info/WHEEL
CommonlyTools-2.1.3.dist-info/top_level.txt
CommonlyTools-2.1.3.dist-info/RECORD
