Metadata-Version: 2.1
Name: CommonlyTools
Version: 2.1.3
Summary: You will use Python easily!
Home-page: https://github.com/maxgamil110331/CommonlyTools
Author: MaxPython110331
Author-email: max.gamil110331@gmail.com
License: MIT
Keywords: CommonlyTools
Platform: UNKNOWN
Classifier: Programming Language :: Python :: 3
Classifier: License :: OSI Approved :: MIT License
Classifier: Operating System :: OS Independent
Requires-Python: >=3.6
Requires-Dist: requests
Requires-Dist: datetime
